muskrat/__init__.py
muskrat/allocator.py
muskrat/class_generator.py
muskrat/connectivity.py
muskrat/cursor.py
muskrat/defaults.py
muskrat/filters.py
muskrat/parser.py
muskrat/pattern.py
muskrat/txt_tree_generator.py
muskrat/xml_generator.py
muskrat-1.0.13.1.dist-info/METADATA
muskrat-1.0.13.1.dist-info/RECORD
muskrat-1.0.13.1.dist-info/WHEEL
muskrat-1.0.13.1.dist-info/top_level.txt
tests/__init__.py
tests/test_exec.py
tests/test_framing_1.py
tests/test_helloworld.py
tests/test_lorem_ipsum.py
tests/test_multiple_ws.py
tests/test_paired_types_group.py
tests/test_parser-get.py
tests/test_tracker_boxes.py
tests/test_txt_tree.py
tests/test_xml_query.py
