Metadata-Version: 2.1
Name: muskrat
Version: 1.0.13.1
Summary: Minimalistic non-BNF text parser
Home-page: https://github.com/prodotiscus/muskrat
Author: Fyodor Sizov
Author-email: f.sizov@yandex.ru
License: UNKNOWN
Platform: UNKNOWN
Classifier: Programming Language :: Python :: 3
Classifier: Operating System :: OS Independent
